pyjavaproperties.py
pyjavaproperties_test.py
pyjavaproperties-0.7.dist-info/LICENSE
pyjavaproperties-0.7.dist-info/METADATA
pyjavaproperties-0.7.dist-info/WHEEL
pyjavaproperties-0.7.dist-info/top_level.txt
pyjavaproperties-0.7.dist-info/RECORD
