Metadata-Version: 1.1
Name: pyjavaproperties
Version: 0.7
Summary: Python replacement for java.util.Properties.
Home-page: https://bitbucket.org/skeptichacker/pyjavaproperties/
Author: Anand B Pillai
Author-email: anandpillai@letterboxes.org
License: MIT License
Platform: UNKNOWN
Classifier: Development Status :: 4 - Beta
Classifier: Intended Audience :: Developers
Classifier: License :: OSI Approved :: MIT License
Classifier: Topic :: Software Development :: Libraries
Classifier: Topic :: Software Development :: Libraries :: Python Modules
